smart_webdriver_manager/__init__.py
smart_webdriver_manager/browser.py
smart_webdriver_manager/cache.py
smart_webdriver_manager/context.py
smart_webdriver_manager/driver.py
smart_webdriver_manager/utils.py
smart_webdriver_manager-0.8.0.dist-info/LICENSE
smart_webdriver_manager-0.8.0.dist-info/METADATA
smart_webdriver_manager-0.8.0.dist-info/WHEEL
smart_webdriver_manager-0.8.0.dist-info/RECORD
