Metadata-Version: 2.3
Name: smart-webdriver-manager
Version: 0.8.0
Summary: A smart webdriver and browser manager
License: MIT
Author: bissli
Requires-Python: >=3.8,<4.0
Classifier: Development Status :: 5 - Production/Stable
Classifier: Intended Audience :: Developers
Classifier: License :: OSI Approved :: Apache Software License
Classifier: License :: OSI Approved :: MIT License
Classifier: Natural Language :: English
Classifier: Programming Language :: Python :: 3
Classifier: Programming Language :: Python :: 3.8
Classifier: Programming Language :: Python :: 3.9
Classifier: Programming Language :: Python :: 3.10
Classifier: Programming Language :: Python :: 3.11
Classifier: Programming Language :: Python :: 3.12
Classifier: Programming Language :: Python :: 3.13
Classifier: Programming Language :: Python :: 3 :: Only
Classifier: Topic :: Software Development :: Libraries
Provides-Extra: test
Requires-Dist: asserts ; extra == "test"
Requires-Dist: backoff
Requires-Dist: bump2version ; extra == "test"
Requires-Dist: mock (>=4.0.3,<5.0.0) ; extra == "test"
Requires-Dist: platformdirs
Requires-Dist: pytest ; extra == "test"
Requires-Dist: pytest-cov ; extra == "test"
Requires-Dist: requests
Requires-Dist: selenium (>=4.1.0,<5.0.0) ; extra == "test"
Requires-Dist: tqdm
Project-URL: Repository, https://github.com/bissli/smart-webdriver-manager
